LICENSE
README.md
setup.py
FrameNet/Frame.c
FrameNet/Frame.pxd
FrameNet/Frame.pyx
FrameNet/FrameElement.c
FrameNet/FrameElement.pxd
FrameNet/FrameElement.pyx
FrameNet/FrameElementList.c
FrameNet/FrameElementList.pxd
FrameNet/FrameElementList.pyx
FrameNet/FrameNet.c
FrameNet/FrameNet.pxd
FrameNet/FrameNet.pyx
FrameNet/__init__.py
FrameNet/data/__init__.py
FrameNet/data/framenet.xml
NlpToolkit_FrameNet_Cy.egg-info/PKG-INFO
NlpToolkit_FrameNet_Cy.egg-info/SOURCES.txt
NlpToolkit_FrameNet_Cy.egg-info/dependency_links.txt
NlpToolkit_FrameNet_Cy.egg-info/top_level.txt
nlptoolkit_framenet_cy.egg-info/PKG-INFO
nlptoolkit_framenet_cy.egg-info/SOURCES.txt
nlptoolkit_framenet_cy.egg-info/dependency_links.txt
nlptoolkit_framenet_cy.egg-info/top_level.txt