Metadata-Version: 2.1
Name: nlptoolkit-framenet-cy
Version: 1.0.11
Summary: FrameNet library
Home-page: https://github.com/StarlangSoftware/TurkishFrameNet-Cy
Author: olcaytaner
Author-email: olcay.yildiz@ozyegin.edu.tr
License: UNKNOWN
Platform: UNKNOWN
